{
	"adult": false,
	"backdrop_path": "/wygUDDRNpeKUnkekRGeLCZM93tA.jpg",
	"belongs_to_collection": {
		"id": 115570,
		"name": "Star Trek: The Next Generation Collection",
		"poster_path": "/sddV6vaUC6x37icJS3opIXTXB07.jpg",
		"backdrop_path": "/r7MMQenUURHhAVHFymtOb8AX4Bm.jpg"
	},
	"budget": 46000000,
	"genres": [
		{
			"id": 878,
			"name": "Science Fiction"
		},
		{
			"id": 28,
			"name": "Action"
		},
		{
			"id": 12,
			"name": "Adventure"
		},
		{
			"id": 53,
			"name": "Thriller"
		}
	],
	"homepage": "https://www.paramountmovies.com/movies/star-trek-viii-first-contact",
	"id": 199,
	"imdb_id": "tt0117731",
	"origin_country": ["US"],
	"original_language": "en",
	"original_title": "Star Trek: First Contact",
	"overview": "The Borg, a relentless race of cyborgs, are on a direct course for Earth. Violating orders to stay away from the battle, Captain Picard and the crew of the newly-commissioned USS Enterprise E pursue the Borg back in time to prevent the invaders from changing Federation history and assimilating the galaxy.",
	"popularity": 19.456,
	"poster_path": "/vrC1lkTktFQ4AqBfqf4PXoDDLcw.jpg",
	"production_companies": [
		{
			"id": 4,
			"logo_path": "/gz66EfNoYPqHTYI4q9UEN4CbHRc.png",
			"name": "Paramount Pictures",
			"origin_country": "US"
		}
	],
	"production_countries": [
		{
			"iso_3166_1": "US",
			"name": "United States of America"
		}
	],
	"release_date": "1996-11-22",
	"revenue": 146027888,
	"runtime": 111,
	"spoken_languages": [
		{
			"english_name": "English",
			"iso_639_1": "en",
			"name": "English"
		}
	],
	"status": "Released",
	"tagline": "Resistance is futile.",
	"title": "Star Trek: First Contact",
	"video": false,
	"vote_average": 7.29,
	"vote_count": 1780,
	"cast": [
		{
			"adult": false,
			"gender": 2,
			"id": 2387,
			"known_for_department": "Acting",
			"name": "Patrick Stewart",
			"original_name": "Patrick Stewart",
			"popularity": 23.09,
			"profile_path": "/wEy5qSDT5jT3ZASc2hbwi59voPL.jpg",
			"cast_id": 19,
			"character": "Captain Jean-Luc Picard",
			"credit_id": "52fe4226c3a36847f8007ba3",
			"order": 0
		},
		{
			"adult": false,
			"gender": 2,
			"id": 2388,
			"known_for_department": "Acting",
			"name": "Jonathan Frakes",
			"original_name": "Jonathan Frakes",
			"popularity": 9.323,
			"profile_path": "/l5leJ7eBPwvRL3zhsy7JUtKhSFH.jpg",
			"cast_id": 25,
			"character": "Commander William T. Riker",
			"credit_id": "52fe4226c3a36847f8007bb7",
			"order": 1
		},
		{
			"adult": false,
			"gender": 2,
			"id": 1213786,
			"known_for_department": "Acting",
			"name": "Brent Spiner",
			"original_name": "Brent Spiner",
			"popularity": 19.361,
			"profile_path": "/wHaOTfxOEKOPssDYaSSB5zenml4.jpg",
			"cast_id": 27,
			"character": "Lieutenant Commander Data",
			"credit_id": "52fe4226c3a36847f8007bbf",
			"order": 2
		},
		{
			"adult": false,
			"gender": 2,
			"id": 2390,
			"known_for_department": "Acting",
			"name": "LeVar Burton",
			"original_name": "LeVar Burton",
			"popularity": 5.293,
			"profile_path": "/tC74tISKpFGmJkrw24MMLix5nNa.jpg",
			"cast_id": 21,
			"character": "Lieutenant Commander Geordi La Forge",
			"credit_id": "52fe4226c3a36847f8007ba7",
			"order": 3
		},
		{
			"adult": false,
			"gender": 2,
			"id": 2391,
			"known_for_department": "Acting",
			"name": "Michael Dorn",
			"original_name": "Michael Dorn",
			"popularity": 13.21,
			"profile_path": "/55xWHDtf7xHFdS6IKicqVzEfTo7.jpg",
			"cast_id": 22,
			"character": "Lieutenant Commander Worf",
			"credit_id": "52fe4226c3a36847f8007bab",
			"order": 4
		},
		{
			"adult": false,
			"gender": 1,
			"id": 2392,
			"known_for_department": "Acting",
			"name": "Gates McFadden",
			"original_name": "Gates McFadden",
			"popularity": 6.707,
			"profile_path": "/5z4rWmLHBHydQRwLHldQllIDq9x.jpg",
			"cast_id": 23,
			"character": "Commander Beverly Crusher",
			"credit_id": "52fe4226c3a36847f8007baf",
			"order": 5
		},
		{
			"adult": false,
			"gender": 1,
			"id": 2393,
			"known_for_department": "Acting",
			"name": "Marina Sirtis",
			"original_name": "Marina Sirtis",
			"popularity": 20.938,
			"profile_path": "/9HIj6m9mGiJE9QF6P48XITU4wbz.jpg",
			"cast_id": 24,
			"character": "Counselor Deanna Troi",
			"credit_id": "52fe4226c3a36847f8007bb3",
			"order": 6
		},
		{
			"adult": false,
			"gender": 2,
			"id": 2505,
			"known_for_department": "Acting",
			"name": "James Cromwell",
			"original_name": "James Cromwell",
			"popularity": 20.423,
			"profile_path": "/vpNQQbM5PtxsYmVm4oh79SGFyUK.jpg",
			"cast_id": 5,
			"character": "Dr. Zefram Cochrane",
			"credit_id": "52fe4226c3a36847f8007b57",
			"order": 7
		},
		{
			"adult": false,
			"gender": 1,
			"id": 1981,
			"known_for_department": "Acting",
			"name": "Alfre Woodard",
			"original_name": "Alfre Woodard",
			"popularity": 15.917,
			"profile_path": "/bD8G3ZWmENq4pNWVqeQfPXPUoTN.jpg",
			"cast_id": 6,
			"character": "Lily Sloane",
			"credit_id": "52fe4226c3a36847f8007b5b",
			"order": 8
		},
		{
			"adult": false,
			"gender": 1,
			"id": 2506,
			"known_for_department": "Acting",
			"name": "Alice Krige",
			"original_name": "Alice Krige",
			"popularity": 16.957,
			"profile_path": "/gwkI4FAYnhkp9NWV3meATzQql0v.jpg",
			"cast_id": 7,
			"character": "Borg Queen",
			"credit_id": "52fe4226c3a36847f8007b5f",
			"order": 9
		},
		{
			"adult": false,
			"gender": 2,
			"id": 2203,
			"known_for_department": "Acting",
			"name": "Neal McDonough",
			"original_name": "Neal McDonough",
			"popularity": 43.365,
			"profile_path": "/3mI3i1CpjATSCta1Tb2qsyl1KCh.jpg",
			"cast_id": 8,
			"character": "Lieutenant Hawk",
			"credit_id": "52fe4226c3a36847f8007b63",
			"order": 10
		},
		{
			"adult": false,
			"gender": 2,
			"id": 28248,
			"known_for_department": "Acting",
			"name": "Dwight Schultz",
			"original_name": "Dwight Schultz",
			"popularity": 13.081,
			"profile_path": "/kVXkC94gNdSWRvDAs0DqBCduJ4S.jpg",
			"cast_id": 26,
			"character": "Lieutenant Barclay",
			"credit_id": "52fe4226c3a36847f8007bbb",
			"order": 11
		},
		{
			"adult": false,
			"gender": 1,
			"id": 1368723,
			"known_for_department": "Acting",
			"name": "Cameron Oppenheimer",
			"original_name": "Cameron Oppenheimer",
			"popularity": 1.904,
			"profile_path": null,
			"cast_id": 32,
			"character": "Ensign Kellogg",
			"credit_id": "54298c6d0e0a260a30000073",
			"order": 12
		},
		{
			"adult": false,
			"gender": 2,
			"id": 16180,
			"known_for_department": "Acting",
			"name": "Robert Picardo",
			"original_name": "Robert Picardo",
			"popularity": 8.68,
			"profile_path": "/9TOY0mhWRMlU5Ur8QHMoDecWs2n.jpg",
			"cast_id": 33,
			"character": "Enterprise EMH",
			"credit_id": "5764b5079251413fde0003a2",
			"order": 13
		},
		{
			"adult": false,
			"gender": 2,
			"id": 36801,
			"known_for_department": "Acting",
			"name": "Adam Scott",
			"original_name": "Adam Scott",
			"popularity": 29.329,
			"profile_path": "/b82C29R6fGiPoqIglQ4lzS6q2YX.jpg",
			"cast_id": 34,
			"character": "Defiant Con Officer",
			"credit_id": "5ac129ef0e0a260c4d00b22c",
			"order": 14
		},
		{
			"adult": false,
			"gender": 2,
			"id": 2982330,
			"known_for_department": "Acting",
			"name": "Ray Uhler",
			"original_name": "Ray Uhler",
			"popularity": 0.537,
			"profile_path": "/ettyLpYWMkeqwkDgvtt1oWXA6oB.jpg",
			"cast_id": 189,
			"character": "Holodeck Nightclub Dancer (uncredited)",
			"credit_id": "602e2566cedac400405255ef",
			"order": 15
		},
		{
			"adult": false,
			"gender": 2,
			"id": 1214196,
			"known_for_department": "Acting",
			"name": "Eric Steinberg",
			"original_name": "Eric Steinberg",
			"popularity": 1.933,
			"profile_path": "/wXOO3yEYUVPkUHAWByvLXypG1aG.jpg",
			"cast_id": 190,
			"character": "Porter",
			"credit_id": "60f4780640d0fe0047c69314",
			"order": 16
		},
		{
			"adult": false,
			"gender": 2,
			"id": 1120542,
			"known_for_department": "Acting",
			"name": "Joey Anaya",
			"original_name": "Joey Anaya",
			"popularity": 1.931,
			"profile_path": "/7jx50BLfdd5Y1LQWxXSORO2MuyT.jpg",
			"cast_id": 191,
			"character": "Borg (uncredited)",
			"credit_id": "61dbf4e0a199a6008d06f4a0",
			"order": 17
		},
		{
			"adult": false,
			"gender": 2,
			"id": 130129,
			"known_for_department": "Acting",
			"name": "Don Stark",
			"original_name": "Don Stark",
			"popularity": 10.98,
			"profile_path": "/lkPWvElz5RxR4t4v3hM4SRy5E1j.jpg",
			"cast_id": 193,
			"character": "Nicky the nose",
			"credit_id": "6335b112cb75d1009536dd97",
			"order": 18
		},
		{
			"adult": false,
			"gender": 1,
			"id": 129464,
			"known_for_department": "Acting",
			"name": "Patti Yasutake",
			"original_name": "Patti Yasutake",
			"popularity": 2.251,
			"profile_path": "/aN0GvOYAwTfukFBQ8m2baHQJmaP.jpg",
			"cast_id": 239,
			"character": "Nurse Ogawa",
			"credit_id": "64502112ed96bc012f89273d",
			"order": 19
		},
		{
			"adult": false,
			"gender": 2,
			"id": 1228876,
			"known_for_department": "Acting",
			"name": "Jack Shearer",
			"original_name": "Jack Shearer",
			"popularity": 2.934,
			"profile_path": "/93sSC5PtmLR1CyAjyguASWz1UDw.jpg",
			"cast_id": 240,
			"character": "Admiral Hayes",
			"credit_id": "6450214c8c0a480121644f8d",
			"order": 20
		},
		{
			"adult": false,
			"gender": 2,
			"id": 1175469,
			"known_for_department": "Acting",
			"name": "Michael Horton",
			"original_name": "Michael Horton",
			"popularity": 2.776,
			"profile_path": null,
			"cast_id": 241,
			"character": "Security Officer",
			"credit_id": "6450217d0257640140e54367",
			"order": 21
		},
		{
			"adult": false,
			"gender": 2,
			"id": 29445,
			"known_for_department": "Acting",
			"name": "Ethan Phillips",
			"original_name": "Ethan Phillips",
			"popularity": 8.84,
			"profile_path": "/npr6XzOaGJauOBV1ydaqmX6T5hl.jpg",
			"cast_id": 242,
			"character": "Holodock Nightclub Maitre d' (uncredited)",
			"credit_id": "64502b683c3ab0014c1d11a7",
			"order": 22
		},
		{
			"adult": false,
			"gender": 1,
			"id": 1755,
			"known_for_department": "Acting",
			"name": "Majel Barrett",
			"original_name": "Majel Barrett",
			"popularity": 7.522,
			"profile_path": "/uTnxd737sEFgc6hVrFgUC5TwzfW.jpg",
			"cast_id": 243,
			"character": "Computer (voice)",
			"credit_id": "64561afec3c891010418e3d9",
			"order": 23
		}
	],
	"crew": [
		{
			"adult": false,
			"gender": 2,
			"id": 2386,
			"known_for_department": "Production",
			"name": "Brannon Braga",
			"original_name": "Brannon Braga",
			"popularity": 4.955,
			"profile_path": "/e2lvaxWUG5dcbl36BEi4po6M0YB.jpg",
			"credit_id": "52fe4226c3a36847f8007b99",
			"department": "Writing",
			"job": "Screenplay"
		},
		{
			"adult": false,
			"gender": 2,
			"id": 1760,
			"known_for_department": "Sound",
			"name": "Jerry Goldsmith",
			"original_name": "Jerry Goldsmith",
			"popularity": 7.298,
			"profile_path": "/uf7jSAculrBbEwdWWAPu6Rs9bXz.jpg",
			"credit_id": "52fe4226c3a36847f8007b6f",
			"department": "Sound",
			"job": "Original Music Composer"
		},
		{
			"adult": false,
			"gender": 2,
			"id": 2504,
			"known_for_department": "Production",
			"name": "Marty Hornstein",
			"original_name": "Marty Hornstein",
			"popularity": 0.741,
			"profile_path": null,
			"credit_id": "52fe4226c3a36847f8007b4d",
			"department": "Production",
			"job": "Executive Producer"
		},
		{
			"adult": false,
			"gender": 2,
			"id": 2512,
			"known_for_department": "Editing",
			"name": "John W. Wheeler",
			"original_name": "John W. Wheeler",
			"popularity": 0.368,
			"profile_path": null,
			"credit_id": "52fe4226c3a36847f8007b8d",
			"department": "Editing",
			"job": "Editor"
		},
		{
			"adult": false,
			"gender": 2,
			"id": 2388,
			"known_for_department": "Acting",
			"name": "Jonathan Frakes",
			"original_name": "Jonathan Frakes",
			"popularity": 9.323,
			"profile_path": "/l5leJ7eBPwvRL3zhsy7JUtKhSFH.jpg",
			"credit_id": "52fe4226c3a36847f8007b41",
			"department": "Directing",
			"job": "Director"
		},
		{
			"adult": false,
			"gender": 2,
			"id": 2507,
			"known_for_department": "Camera",
			"name": "Matthew F. Leonetti",
			"original_name": "Matthew F. Leonetti",
			"popularity": 3.587,
			"profile_path": "/v9kwWIkNkanReGoFfJA1vrLBUDP.jpg",
			"credit_id": "52fe4226c3a36847f8007b69",
			"department": "Camera",
			"job": "Director of Photography"
		},
		{
			"adult": false,
			"gender": 2,
			"id": 2083,
			"known_for_department": "Art",
			"name": "Herman F. Zimmerman",
			"original_name": "Herman F. Zimmerman",
			"popularity": 0.577,
			"profile_path": null,
			"credit_id": "52fe4226c3a36847f8007b75",
			"department": "Art",
			"job": "Production Design"
		},
		{
			"adult": false,
			"gender": 2,
			"id": 2383,
			"known_for_department": "Production",
			"name": "Peter Lauritson",
			"original_name": "Peter Lauritson",
			"popularity": 1.343,
			"profile_path": null,
			"credit_id": "52fe4226c3a36847f8007b53",
			"department": "Production",
			"job": "Producer"
		},
		{
			"adult": false,
			"gender": 2,
			"id": 2400,
			"known_for_department": "Production",
			"name": "Ron Surma",
			"original_name": "Ron Surma",
			"popularity": 1.493,
			"profile_path": null,
			"credit_id": "52fe4226c3a36847f8007b81",
			"department": "Production",
			"job": "Casting"
		},
		{
			"adult": false,
			"gender": 2,
			"id": 2385,
			"known_for_department": "Writing",
			"name": "Ronald D. Moore",
			"original_name": "Ronald D. Moore",
			"popularity": 7.074,
			"profile_path": "/6A086Blwpv0nuckrzPgvETlkfo1.jpg",
			"credit_id": "52fe4226c3a36847f8007b9f",
			"department": "Writing",
			"job": "Screenplay"
		},
		{
			"adult": false,
			"gender": 0,
			"id": 2511,
			"known_for_department": "Acting",
			"name": "Anastasia Emmons",
			"original_name": "Anastasia Emmons",
			"popularity": 1.852,
			"profile_path": null,
			"credit_id": "52fe4226c3a36847f8007b87",
			"department": "Editing",
			"job": "Editor"
		},
		{
			"adult": false,
			"gender": 2,
			"id": 2508,
			"known_for_department": "Art",
			"name": "Ron Wilkinson",
			"original_name": "Ron Wilkinson",
			"popularity": 0.001,
			"profile_path": null,
			"credit_id": "52fe4226c3a36847f8007b93",
			"department": "Art",
			"job": "Art Direction"
		},
		{
			"adult": false,
			"gender": 1,
			"id": 2399,
			"known_for_department": "Production",
			"name": "Junie Lowry-Johnson",
			"original_name": "Junie Lowry-Johnson",
			"popularity": 1.572,
			"profile_path": "/1WIEz9uYLpsv28tcvnH97OgcYoF.jpg",
			"credit_id": "52fe4226c3a36847f8007b7b",
			"department": "Production",
			"job": "Casting"
		},
		{
			"adult": false,
			"gender": 2,
			"id": 3486384,
			"known_for_department": "Production",
			"name": "Daryl Tucker",
			"original_name": "Daryl Tucker",
			"popularity": 1.721,
			"profile_path": "/sG0W0X9ytd0TYzN3PBymqsMBmNl.jpg",
			"credit_id": "6245eb0e6dc507005de90857",
			"department": "Camera",
			"job": "Grip"
		},
		{
			"adult": false,
			"gender": 1,
			"id": 1319746,
			"known_for_department": "Costume & Make-Up",
			"name": "Sarah Shawe",
			"original_name": "Sarah Shawe",
			"popularity": 0.001,
			"profile_path": null,
			"credit_id": "5374926c0e0a267c59003946",
			"department": "Costume & Make-Up",
			"job": "Costume Supervisor"
		},
		{
			"adult": false,
			"gender": 2,
			"id": 796,
			"known_for_department": "Art",
			"name": "John M. Dwyer",
			"original_name": "John M. Dwyer",
			"popularity": 1.219,
			"profile_path": null,
			"credit_id": "537491aec3a368150f002753",
			"department": "Art",
			"job": "Set Decoration"
		},
		{
			"adult": false,
			"gender": 1,
			"id": 22107,
			"known_for_department": "Costume & Make-Up",
			"name": "Deborah Everton",
			"original_name": "Deborah Everton",
			"popularity": 1.572,
			"profile_path": "/5VwTUOm9iDxVhFrmtf4bmQi2QYT.jpg",
			"credit_id": "53749194c3a3681528002740",
			"department": "Costume & Make-Up",
			"job": "Costume Design"
		},
		{
			"adult": false,
			"gender": 0,
			"id": 2397,
			"known_for_department": "Costume & Make-Up",
			"name": "Robert Blackman",
			"original_name": "Robert Blackman",
			"popularity": 1.547,
			"profile_path": null,
			"credit_id": "537491eec3a3681539002661",
			"department": "Costume & Make-Up",
			"job": "Costume Design"
		},
		{
			"adult": false,
			"gender": 1,
			"id": 62568,
			"known_for_department": "Acting",
			"name": "Rosine 'Ace' Hatem",
			"original_name": "Rosine 'Ace' Hatem",
			"popularity": 2.071,
			"profile_path": "/6gj1H7jtkAJOl39oXDFEglbl5zH.jpg",
			"credit_id": "6422102c2dc9dc007f0ddb04",
			"department": "Crew",
			"job": "Stunts"
		},
		{
			"adult": false,
			"gender": 1,
			"id": 999680,
			"known_for_department": "Crew",
			"name": "Debbie Lynn Ross",
			"original_name": "Debbie Lynn Ross",
			"popularity": 5.644,
			"profile_path": null,
			"credit_id": "64262deb01b1ca00d5e70a0f",
			"department": "Crew",
			"job": "Stunts"
		},
		{
			"adult": false,
			"gender": 2,
			"id": 1400371,
			"known_for_department": "Crew",
			"name": "James M. Halty",
			"original_name": "James M. Halty",
			"popularity": 1.753,
			"profile_path": null,
			"credit_id": "64262e7e960cde00771205b0",
			"department": "Crew",
			"job": "Stunts"
		},
		{
			"adult": false,
			"gender": 2,
			"id": 2299954,
			"known_for_department": "Crew",
			"name": "Billy Hank Hooker",
			"original_name": "Billy Hank Hooker",
			"popularity": 1.536,
			"profile_path": null,
			"credit_id": "64262e978de0ae00f4bef254",
			"department": "Crew",
			"job": "Stunts"
		},
		{
			"adult": false,
			"gender": 2,
			"id": 1464039,
			"known_for_department": "Acting",
			"name": "John Rottger",
			"original_name": "John Rottger",
			"popularity": 2.12,
			"profile_path": "/A1onpu9DRpD9POvslF5HYjpEyJP.jpg",
			"credit_id": "64262f6f01b1ca00e3a9c48e",
			"department": "Crew",
			"job": "Stunts"
		},
		{
			"adult": false,
			"gender": 2,
			"id": 1463665,
			"known_for_department": "Crew",
			"name": "Tony Donno",
			"original_name": "Tony Donno",
			"popularity": 3.121,
			"profile_path": "/1KYcm6ZA5ZnRb9p7ABDdYZ1AwAI.jpg",
			"credit_id": "64262e337f6c8d007712c882",
			"department": "Crew",
			"job": "Stunts"
		},
		{
			"adult": false,
			"gender": 2,
			"id": 1771760,
			"known_for_department": "Crew",
			"name": "Richard Epper",
			"original_name": "Richard Epper",
			"popularity": 3.324,
			"profile_path": null,
			"credit_id": "64262e638de0ae00f4bef211",
			"department": "Crew",
			"job": "Stunts"
		},
		{
			"adult": false,
			"gender": 0,
			"id": 2770569,
			"known_for_department": "Crew",
			"name": "Wayne King",
			"original_name": "Wayne King",
			"popularity": 0.27,
			"profile_path": null,
			"credit_id": "64262ec7960cde00e0bbfc9e",
			"department": "Crew",
			"job": "Stunts"
		},
		{
			"adult": false,
			"gender": 2,
			"id": 2095075,
			"known_for_department": "Acting",
			"name": "John Nowak",
			"original_name": "John Nowak",
			"popularity": 0.153,
			"profile_path": null,
			"credit_id": "64262f2c01b1ca0097fccc30",
			"department": "Crew",
			"job": "Stunts"
		},
		{
			"adult": false,
			"gender": 2,
			"id": 165640,
			"known_for_department": "Acting",
			"name": "James Ryan",
			"original_name": "James Ryan",
			"popularity": 2.675,
			"profile_path": "/nuCNqLw8Hw7B7J1qRzKi998tRkw.jpg",
			"credit_id": "64262f7c8de0ae00d5f20cc5",
			"department": "Crew",
			"job": "Stunts"
		},
		{
			"adult": false,
			"gender": 2,
			"id": 1339453,
			"known_for_department": "Crew",
			"name": "Thomas Robinson Harper",
			"original_name": "Thomas Robinson Harper",
			"popularity": 1.434,
			"profile_path": "/xPFdDSXceVebYdcYOKpkTpncWoC.jpg",
			"credit_id": "64262e9e7f6c8d007712c8e3",
			"department": "Crew",
			"job": "Stunts"
		},
		{
			"adult": false,
			"gender": 2,
			"id": 106475,
			"known_for_department": "Acting",
			"name": "Tom Poster",
			"original_name": "Tom Poster",
			"popularity": 0.417,
			"profile_path": null,
			"credit_id": "64262f4a7f6c8d00b61b5946",
			"department": "Crew",
			"job": "Stunts"
		},
		{
			"adult": false,
			"gender": 2,
			"id": 158145,
			"known_for_department": "Crew",
			"name": "Craig Shugart",
			"original_name": "Craig Shugart",
			"popularity": 1.123,
			"profile_path": null,
			"credit_id": "64262f697f6c8d00b61b5966",
			"department": "Crew",
			"job": "Stunts"
		},
		{
			"adult": false,
			"gender": 2,
			"id": 944478,
			"known_for_department": "Acting",
			"name": "Chic Daniel",
			"original_name": "Chic Daniel",
			"popularity": 4.831,
			"profile_path": "/mLf3j2ner6ZJKpmrbZxway8uR7u.jpg",
			"credit_id": "64262e1b7f6c8d01132287b6",
			"department": "Crew",
			"job": "Stunts"
		},
		{
			"adult": false,
			"gender": 2,
			"id": 1404815,
			"known_for_department": "Crew",
			"name": "Steve Picerni",
			"original_name": "Steve Picerni",
			"popularity": 2.125,
			"profile_path": "/5KknfuSZlxvOcrbNWuRaVVc3eYX.jpg",
			"credit_id": "64262f116905fb009ad7a1a6",
			"department": "Crew",
			"job": "Stunts"
		},
		{
			"adult": false,
			"gender": 2,
			"id": 1502517,
			"known_for_department": "Crew",
			"name": "Manny Perry",
			"original_name": "Manny Perry",
			"popularity": 2.721,
			"profile_path": "/aCYOiEZ7LkqJUEce0PsPVx6GWo0.jpg",
			"credit_id": "64262f23c044290236ca72e3",
			"department": "Crew",
			"job": "Stunts"
		},
		{
			"adult": false,
			"gender": 0,
			"id": 2550152,
			"known_for_department": "Directing",
			"name": "Jerry Fleck",
			"original_name": "Jerry Fleck",
			"popularity": 0.283,
			"profile_path": null,
			"credit_id": "64262dcda3e4ba0095f1fe32",
			"department": "Directing",
			"job": "First Assistant Director"
		},
		{
			"adult": false,
			"gender": 2,
			"id": 2002921,
			"known_for_department": "Crew",
			"name": "Andy Epper",
			"original_name": "Andy Epper",
			"popularity": 0.627,
			"profile_path": null,
			"credit_id": "64262e4ac04429026b126f33",
			"department": "Crew",
			"job": "Stunts"
		},
		{
			"adult": false,
			"gender": 2,
			"id": 194654,
			"known_for_department": "Crew",
			"name": "John C. Meier",
			"original_name": "John C. Meier",
			"popularity": 5.22,
			"profile_path": "/kP7rVXlfnKQF9YHEoTJonYiHsBm.jpg",
			"credit_id": "64262eee01b1ca007779c9e6",
			"department": "Crew",
			"job": "Stunts"
		},
		{
			"adult": false,
			"gender": 2,
			"id": 2154322,
			"known_for_department": "Crew",
			"name": "Monte Rex Perlin",
			"original_name": "Monte Rex Perlin",
			"popularity": 1.45,
			"profile_path": null,
			"credit_id": "64262f17c04429021304e3be",
			"department": "Crew",
			"job": "Stunts"
		},
		{
			"adult": false,
			"gender": 0,
			"id": 1404697,
			"known_for_department": "Crew",
			"name": "Jimmy Romano",
			"original_name": "Jimmy Romano",
			"popularity": 2.162,
			"profile_path": null,
			"credit_id": "64262f4301b1ca0113cae65c",
			"department": "Crew",
			"job": "Stunts"
		},
		{
			"adult": false,
			"gender": 2,
			"id": 161824,
			"known_for_department": "Crew",
			"name": "Ronnie Rondell Jr.",
			"original_name": "Ronnie Rondell Jr.",
			"popularity": 3.819,
			"profile_path": null,
			"credit_id": "64262df08de0ae01134e9962",
			"department": "Crew",
			"job": "Stunt Coordinator"
		},
		{
			"adult": false,
			"gender": 2,
			"id": 9436,
			"known_for_department": "Crew",
			"name": "Kenny Alexander",
			"original_name": "Kenny Alexander",
			"popularity": 3.059,
			"profile_path": null,
			"credit_id": "64262e0301b1ca00e3a9c364",
			"department": "Crew",
			"job": "Stunts"
		},
		{
			"adult": false,
			"gender": 2,
			"id": 2148423,
			"known_for_department": "Crew",
			"name": "Bob McGovern",
			"original_name": "Bob McGovern",
			"popularity": 0.428,
			"profile_path": null,
			"credit_id": "64262ecfc044290298cdf374",
			"department": "Crew",
			"job": "Stunts"
		},
		{
			"adult": false,
			"gender": 1,
			"id": 1530090,
			"known_for_department": "Directing",
			"name": "Rosemary C. Cremona",
			"original_name": "Rosemary C. Cremona",
			"popularity": 1.037,
			"profile_path": null,
			"credit_id": "64262dd4c0442901f0016a24",
			"department": "Directing",
			"job": "Second Assistant Director"
		},
		{
			"adult": false,
			"gender": 2,
			"id": 1412253,
			"known_for_department": "Crew",
			"name": "William H. Burton Jr.",
			"original_name": "William H. Burton Jr.",
			"popularity": 1.831,
			"profile_path": null,
			"credit_id": "64262e21a3e4ba0111493fb0",
			"department": "Crew",
			"job": "Stunts"
		},
		{
			"adult": false,
			"gender": 2,
			"id": 1541688,
			"known_for_department": "Crew",
			"name": "Christian J. Fletcher",
			"original_name": "Christian J. Fletcher",
			"popularity": 1.497,
			"profile_path": "/mzhuznfQ2YZsvFk8W6yqlRlsMc6.jpg",
			"credit_id": "64262e7301b1ca007779c98c",
			"department": "Crew",
			"job": "Stunts"
		},
		{
			"adult": false,
			"gender": 2,
			"id": 8432,
			"known_for_department": "Acting",
			"name": "Buddy Joe Hooker",
			"original_name": "Buddy Joe Hooker",
			"popularity": 9.228,
			"profile_path": "/sQkPgACtSAPscomfa650C2hsubm.jpg",
			"credit_id": "64262ebc7f6c8d007712c8f9",
			"department": "Crew",
			"job": "Stunts"
		},
		{
			"adult": false,
			"gender": 2,
			"id": 1638032,
			"known_for_department": "Crew",
			"name": "Dustin Meier",
			"original_name": "Dustin Meier",
			"popularity": 1.268,
			"profile_path": null,
			"credit_id": "64262ee76905fb012608938f",
			"department": "Crew",
			"job": "Stunts"
		},
		{
			"adult": false,
			"gender": 2,
			"id": 161597,
			"known_for_department": "Acting",
			"name": "Gary Epper",
			"original_name": "Gary Epper",
			"popularity": 1.409,
			"profile_path": null,
			"credit_id": "64262e508de0ae00978c064d",
			"department": "Crew",
			"job": "Stunts"
		},
		{
			"adult": false,
			"gender": 2,
			"id": 203950,
			"known_for_department": "Acting",
			"name": "Brian J. Williams",
			"original_name": "Brian J. Williams",
			"popularity": 3.165,
			"profile_path": null,
			"credit_id": "64262dfd7f6c8d00976fd5d1",
			"department": "Crew",
			"job": "Stunt Double"
		},
		{
			"adult": false,
			"gender": 2,
			"id": 1089167,
			"known_for_department": "Acting",
			"name": "Steve DeRelian",
			"original_name": "Steve DeRelian",
			"popularity": 0.574,
			"profile_path": "/9oJhzdLEgOz6phE8AQN7s9miy2M.jpg",
			"credit_id": "64262e556905fb0103226e0c",
			"department": "Crew",
			"job": "Stunts"
		},
		{
			"adult": false,
			"gender": 2,
			"id": 968316,
			"known_for_department": "Crew",
			"name": "Andy Gill",
			"original_name": "Andy Gill",
			"popularity": 1.653,
			"profile_path": "/uphgScM95clUsV8Rb2nwdiqCndX.jpg",
			"credit_id": "64262e6a6905fb00bd098462",
			"department": "Crew",
			"job": "Stunts"
		},
		{
			"adult": false,
			"gender": 2,
			"id": 1905689,
			"known_for_department": "Crew",
			"name": "Gary Guercio",
			"original_name": "Gary Guercio",
			"popularity": 1.093,
			"profile_path": "/hhvXBXpDtROcONucazJfI41kFoC.jpg",
			"credit_id": "64262e8501b1ca0097fccbab",
			"department": "Crew",
			"job": "Stunts"
		},
		{
			"adult": false,
			"gender": 2,
			"id": 92494,
			"known_for_department": "Crew",
			"name": "Kim Robert Koscki",
			"original_name": "Kim Robert Koscki",
			"popularity": 1.077,
			"profile_path": "/gd9TPbYhHlIqK79A1t28j2dyaoz.jpg",
			"credit_id": "64262ed401b1ca0113cae60b",
			"department": "Crew",
			"job": "Stunts"
		},
		{
			"adult": false,
			"gender": 2,
			"id": 1504123,
			"known_for_department": "Acting",
			"name": "Eddy Donno",
			"original_name": "Eddy Donno",
			"popularity": 3.259,
			"profile_path": "/rv7ALEG5UVL3lKcmtzyWZT0j57j.jpg",
			"credit_id": "64262e2c960cde009a968b12",
			"department": "Crew",
			"job": "Stunts"
		},
		{
			"adult": false,
			"gender": 2,
			"id": 1648163,
			"known_for_department": "Crew",
			"name": "Frankie 'G' Garbutt",
			"original_name": "Frankie 'G' Garbutt",
			"popularity": 0.897,
			"profile_path": null,
			"credit_id": "64262e8a6905fb0103226e46",
			"department": "Crew",
			"job": "Stunts"
		},
		{
			"adult": false,
			"gender": 1,
			"id": 1709444,
			"known_for_department": "Crew",
			"name": "Maria R. Kelly",
			"original_name": "Maria R. Kelly",
			"popularity": 1.371,
			"profile_path": null,
			"credit_id": "64262eb68de0ae00f4bef27d",
			"department": "Crew",
			"job": "Stunts"
		},
		{
			"adult": false,
			"gender": 2,
			"id": 1656382,
			"known_for_department": "Crew",
			"name": "Danny Rogers",
			"original_name": "Danny Rogers",
			"popularity": 1.4,
			"profile_path": null,
			"credit_id": "64262f5301b1ca0113cae667",
			"department": "Crew",
			"job": "Stunts"
		},
		{
			"adult": false,
			"gender": 2,
			"id": 16500,
			"known_for_department": "Crew",
			"name": "Mark De Alessandro",
			"original_name": "Mark De Alessandro",
			"popularity": 3.32,
			"profile_path": "/i8OVPh4axVPhTAso3fPEJ86V0v2.jpg",
			"credit_id": "64262e38a3e4ba00b422f16a",
			"department": "Crew",
			"job": "Stunts"
		},
		{
			"adult": false,
			"gender": 1,
			"id": 1544401,
			"known_for_department": "Crew",
			"name": "Joyce McNeal",
			"original_name": "Joyce McNeal",
			"popularity": 0.273,
			"profile_path": null,
			"credit_id": "64262ef67f6c8d00f458ba27",
			"department": "Crew",
			"job": "Stunts"
		},
		{
			"adult": false,
			"gender": 2,
			"id": 1462675,
			"known_for_department": "Crew",
			"name": "Pat Romano",
			"original_name": "Pat Romano",
			"popularity": 7.795,
			"profile_path": "/woxz6mrLAWq7u22lSPSdvEFbEmy.jpg",
			"credit_id": "64262f62960cde007712065d",
			"department": "Crew",
			"job": "Stunts"
		},
		{
			"adult": false,
			"gender": 1,
			"id": 1880383,
			"known_for_department": "Crew",
			"name": "Janet Brady",
			"original_name": "Janet Brady",
			"popularity": 2.042,
			"profile_path": null,
			"credit_id": "64262e14c044290298cdf2e3",
			"department": "Crew",
			"job": "Stunts"
		},
		{
			"adult": false,
			"gender": 2,
			"id": 1576419,
			"known_for_department": "Acting",
			"name": "Kenny Endoso",
			"original_name": "Kenny Endoso",
			"popularity": 7.427,
			"profile_path": "/cVDyTG8I6hdfOQRrgn2oX2hyGRQ.jpg",
			"credit_id": "64262e42a3e4ba00d3ace972",
			"department": "Crew",
			"job": "Stunts"
		},
		{
			"adult": false,
			"gender": 2,
			"id": 1120542,
			"known_for_department": "Acting",
			"name": "Joey Anaya",
			"original_name": "Joey Anaya",
			"popularity": 1.931,
			"profile_path": "/7jx50BLfdd5Y1LQWxXSORO2MuyT.jpg",
			"credit_id": "64262e0b8de0ae00d5f20b76",
			"department": "Crew",
			"job": "Stunts"
		},
		{
			"adult": false,
			"gender": 0,
			"id": 1360101,
			"known_for_department": "Sound",
			"name": "Sarah Monat",
			"original_name": "Sarah Monat",
			"popularity": 2.708,
			"profile_path": null,
			"credit_id": "5b2fa8860e0a2656230055c0",
			"department": "Sound",
			"job": "Foley Artist"
		},
		{
			"adult": false,
			"gender": 2,
			"id": 15847,
			"known_for_department": "Crew",
			"name": "Terry D. Frazee",
			"original_name": "Terry D. Frazee",
			"popularity": 0.785,
			"profile_path": null,
			"credit_id": "5b2fac4c9251417066004f35",
			"department": "Crew",
			"job": "Special Effects Coordinator"
		},
		{
			"adult": false,
			"gender": 0,
			"id": 1606661,
			"known_for_department": "Editing",
			"name": "John McCunn",
			"original_name": "John McCunn",
			"popularity": 0.001,
			"profile_path": null,
			"credit_id": "5b2fb179925141708a0051ec",
			"department": "Visual Effects",
			"job": "Visual Effects Producer"
		},
		{
			"adult": false,
			"gender": 0,
			"id": 2071361,
			"known_for_department": "Sound",
			"name": "Roger Fearing",
			"original_name": "Roger Fearing",
			"popularity": 0.036,
			"profile_path": null,
			"credit_id": "5b2fa7dc9251416dd80047df",
			"department": "Sound",
			"job": "Assistant Sound Editor"
		},
		{
			"adult": false,
			"gender": 0,
			"id": 2071362,
			"known_for_department": "Crew",
			"name": "John Agalsoff Jr.",
			"original_name": "John Agalsoff Jr.",
			"popularity": 0.001,
			"profile_path": null,
			"credit_id": "5b2fa802c3a36843c5006961",
			"department": "Crew",
			"job": "Cableman"
		},
		{
			"adult": false,
			"gender": 2,
			"id": 1341855,
			"known_for_department": "Sound",
			"name": "Ken Dufva",
			"original_name": "Ken Dufva",
			"popularity": 1.716,
			"profile_path": null,
			"credit_id": "5b2fa853c3a3685711006464",
			"department": "Sound",
			"job": "Foley Artist"
		},
		{
			"adult": false,
			"gender": 2,
			"id": 1399861,
			"known_for_department": "Sound",
			"name": "Brad Sherman",
			"original_name": "Brad Sherman",
			"popularity": 0.844,
			"profile_path": null,
			"credit_id": "5b2faa40c3a3685b99004e52",
			"department": "Sound",
			"job": "Sound Re-Recording Mixer"
		},
		{
			"adult": false,
			"gender": 0,
			"id": 2071370,
			"known_for_department": "Crew",
			"name": "Donald T. Black",
			"original_name": "Donald T. Black",
			"popularity": 0.001,
			"profile_path": null,
			"credit_id": "5b2facc59251416dd8004a2e",
			"department": "Crew",
			"job": "Special Effects Assistant"
		},
		{
			"adult": false,
			"gender": 2,
			"id": 2071372,
			"known_for_department": "Crew",
			"name": "Ralph Winiger",
			"original_name": "Ralph Winiger",
			"popularity": 0.001,
			"profile_path": null,
			"credit_id": "5b2facf8c3a368575d0048ac",
			"department": "Crew",
			"job": "Special Effects Assistant"
		},
		{
			"adult": false,
			"gender": 0,
			"id": 1552205,
			"known_for_department": "Sound",
			"name": "Anne Couk",
			"original_name": "Anne Couk",
			"popularity": 0.913,
			"profile_path": null,
			"credit_id": "5b2fa82692514154f9004fa7",
			"department": "Sound",
			"job": "First Assistant Sound Editor"
		},
		{
			"adult": false,
			"gender": 2,
			"id": 373,
			"known_for_department": "Sound",
			"name": "Doug Jackson",
			"original_name": "Doug Jackson",
			"popularity": 0.795,
			"profile_path": null,
			"credit_id": "5b2fa96cc3a3685711006534",
			"department": "Sound",
			"job": "Sound Effects Editor"
		},
		{
			"adult": false,
			"gender": 0,
			"id": 1419255,
			"known_for_department": "Sound",
			"name": "David F. Van Slyke",
			"original_name": "David F. Van Slyke",
			"popularity": 0.312,
			"profile_path": "/uuTqTgD3wirwz4uwYAtkSXN7brV.jpg",
			"credit_id": "5b2fa980c3a368577100714b",
			"department": "Sound",
			"job": "Sound Effects Editor"
		},
		{
			"adult": false,
			"gender": 0,
			"id": 2071374,
			"known_for_department": "Crew",
			"name": "Scott Lingard",
			"original_name": "Scott Lingard",
			"popularity": 0.001,
			"profile_path": null,
			"credit_id": "5b2fad220e0a2656b70057eb",
			"department": "Crew",
			"job": "Special Effects Assistant"
		},
		{
			"adult": false,
			"gender": 2,
			"id": 2043747,
			"known_for_department": "Sound",
			"name": "Bob Baron",
			"original_name": "Bob Baron",
			"popularity": 1.021,
			"profile_path": null,
			"credit_id": "5b2fa7b29251416e8d00571f",
			"department": "Sound",
			"job": "ADR Mixer"
		},
		{
			"adult": false,
			"gender": 0,
			"id": 1401967,
			"known_for_department": "Crew",
			"name": "Alex Jaeger",
			"original_name": "Alex Jaeger",
			"popularity": 0.767,
			"profile_path": null,
			"credit_id": "5b2fb1039251416fa5005bb2",
			"department": "Crew",
			"job": "Visual Effects Art Director"
		},
		{
			"adult": false,
			"gender": 2,
			"id": 83082,
			"known_for_department": "Sound",
			"name": "Joseph F. Brennan",
			"original_name": "Joseph F. Brennan",
			"popularity": 1.119,
			"profile_path": null,
			"credit_id": "5b2fa7eec3a368580d006180",
			"department": "Sound",
			"job": "Boom Operator"
		},
		{
			"adult": false,
			"gender": 2,
			"id": 1400556,
			"known_for_department": "Sound",
			"name": "Ed Callahan",
			"original_name": "Ed Callahan",
			"popularity": 1.649,
			"profile_path": null,
			"credit_id": "5b2fa8e69251417470005246",
			"department": "Sound",
			"job": "Foley Editor"
		},
		{
			"adult": false,
			"gender": 2,
			"id": 1274309,
			"known_for_department": "Sound",
			"name": "Randy Singer",
			"original_name": "Randy Singer",
			"popularity": 2.155,
			"profile_path": null,
			"credit_id": "5b2fa91b0e0a2656df005b86",
			"department": "Sound",
			"job": "Foley Mixer"
		},
		{
			"adult": false,
			"gender": 2,
			"id": 1629423,
			"known_for_department": "Sound",
			"name": "Philip Rogers",
			"original_name": "Philip Rogers",
			"popularity": 2.432,
			"profile_path": null,
			"credit_id": "5b2faa590e0a2656230056a8",
			"department": "Sound",
			"job": "Sound Recordist"
		},
		{
			"adult": false,
			"gender": 2,
			"id": 1015046,
			"known_for_department": "Visual Effects",
			"name": "John Deall",
			"original_name": "John Deall",
			"popularity": 0.083,
			"profile_path": null,
			"credit_id": "5b2fac2cc3a36858cb004b84",
			"department": "Visual Effects",
			"job": "Mechanical Designer"
		},
		{
			"adult": false,
			"gender": 0,
			"id": 3457,
			"known_for_department": "Crew",
			"name": "Logan Frazee",
			"original_name": "Logan Frazee",
			"popularity": 0.552,
			"profile_path": null,
			"credit_id": "5b2face89251416fa20054a9",
			"department": "Crew",
			"job": "Special Effects Assistant"
		},
		{
			"adult": false,
			"gender": 0,
			"id": 1455459,
			"known_for_department": "Visual Effects",
			"name": "Todd Boyce",
			"original_name": "Todd Boyce",
			"popularity": 0.001,
			"profile_path": null,
			"credit_id": "5b2fae0bc3a36858230055ea",
			"department": "Visual Effects",
			"job": "CG Animator"
		},
		{
			"adult": false,
			"gender": 0,
			"id": 2003410,
			"known_for_department": "Visual Effects",
			"name": "Carl Hooper",
			"original_name": "Carl Hooper",
			"popularity": 0.001,
			"profile_path": null,
			"credit_id": "5b2fae1b0e0a2655af005651",
			"department": "Visual Effects",
			"job": "CG Animator"
		},
		{
			"adult": false,
			"gender": 0,
			"id": 2071376,
			"known_for_department": "Visual Effects",
			"name": "Jeffery Yost",
			"original_name": "Jeffery Yost",
			"popularity": 0.001,
			"profile_path": null,
			"credit_id": "5b2fae33c3a368571400531c",
			"department": "Visual Effects",
			"job": "CG Artist"
		},
		{
			"adult": false,
			"gender": 0,
			"id": 1417498,
			"known_for_department": "Sound",
			"name": "Richard Corwin",
			"original_name": "Richard Corwin",
			"popularity": 0.62,
			"profile_path": null,
			"credit_id": "5b2fa8130e0a2655af00531a",
			"department": "Sound",
			"job": "Dialogue Editor"
		},
		{
			"adult": false,
			"gender": 0,
			"id": 71633,
			"known_for_department": "Sound",
			"name": "Jeff Clark",
			"original_name": "Jeff Clark",
			"popularity": 0.535,
			"profile_path": null,
			"credit_id": "5b2fa9a60e0a2656df005bc0",
			"department": "Sound",
			"job": "Sound Effects Editor"
		},
		{
			"adult": false,
			"gender": 0,
			"id": 2071373,
			"known_for_department": "Crew",
			"name": "Samuel E. Price",
			"original_name": "Samuel E. Price",
			"popularity": 0.034,
			"profile_path": null,
			"credit_id": "5b2fad100e0a265764005677",
			"department": "Crew",
			"job": "Special Effects Assistant"
		},
		{
			"adult": false,
			"gender": 1,
			"id": 1546101,
			"known_for_department": "Sound",
			"name": "Tammy Fearing",
			"original_name": "Tammy Fearing",
			"popularity": 2.321,
			"profile_path": null,
			"credit_id": "5b2fa8fbc3a36858b3005f38",
			"department": "Sound",
			"job": "Foley Editor"
		},
		{
			"adult": false,
			"gender": 2,
			"id": 8762,
			"known_for_department": "Sound",
			"name": "Scott G.G. Haller",
			"original_name": "Scott G.G. Haller",
			"popularity": 2.359,
			"profile_path": null,
			"credit_id": "5b2fa9570e0a26560600522f",
			"department": "Sound",
			"job": "Sound Effects Editor"
		},
		{
			"adult": false,
			"gender": 0,
			"id": 2071369,
			"known_for_department": "Crew",
			"name": "Jason Bardis",
			"original_name": "Jason Bardis",
			"popularity": 0.001,
			"profile_path": null,
			"credit_id": "5b2fac8e9251416e58004c04",
			"department": "Crew",
			"job": "Special Effects Technician"
		},
		{
			"adult": false,
			"gender": 0,
			"id": 1227173,
			"known_for_department": "Sound",
			"name": "Robin Harlan",
			"original_name": "Robin Harlan",
			"popularity": 2.316,
			"profile_path": null,
			"credit_id": "5b2fa8739251416e8d005786",
			"department": "Sound",
			"job": "Foley"
		},
		{
			"adult": false,
			"gender": 2,
			"id": 113043,
			"known_for_department": "Sound",
			"name": "Scott Curtis",
			"original_name": "Scott Curtis",
			"popularity": 2.178,
			"profile_path": null,
			"credit_id": "5b2fa8b8c3a3685714005012",
			"department": "Sound",
			"job": "Foley Editor"
		},
		{
			"adult": false,
			"gender": 2,
			"id": 1378228,
			"known_for_department": "Sound",
			"name": "Steve Pederson",
			"original_name": "Steve Pederson",
			"popularity": 0.549,
			"profile_path": null,
			"credit_id": "5b2faa18c3a3685900003927",
			"department": "Sound",
			"job": "Sound Re-Recording Mixer"
		},
		{
			"adult": false,
			"gender": 0,
			"id": 2057524,
			"known_for_department": "Visual Effects",
			"name": "Dennis Turner",
			"original_name": "Dennis Turner",
			"popularity": 0.039,
			"profile_path": null,
			"credit_id": "5b2faecc9251416dd8004b54",
			"department": "Crew",
			"job": "Sequence Supervisor"
		},
		{
			"adult": false,
			"gender": 2,
			"id": 1577475,
			"known_for_department": "Sound",
			"name": "Robert Morrisey",
			"original_name": "Robert Morrisey",
			"popularity": 0.598,
			"profile_path": null,
			"credit_id": "5b2fa7c892514154f9004f8b",
			"department": "Sound",
			"job": "Assistant Sound Editor"
		},
		{
			"adult": false,
			"gender": 2,
			"id": 1170025,
			"known_for_department": "Sound",
			"name": "David Lee Fein",
			"original_name": "David Lee Fein",
			"popularity": 0.809,
			"profile_path": null,
			"credit_id": "5b2fa863c3a3685900003883",
			"department": "Sound",
			"job": "Foley Artist"
		},
		{
			"adult": false,
			"gender": 2,
			"id": 1538705,
			"known_for_department": "Sound",
			"name": "Thomas Causey",
			"original_name": "Thomas Causey",
			"popularity": 0.612,
			"profile_path": null,
			"credit_id": "5b2fa9c2c3a36857cf006338",
			"department": "Sound",
			"job": "Sound Mixer"
		},
		{
			"adult": false,
			"gender": 2,
			"id": 1551523,
			"known_for_department": "Sound",
			"name": "Robert Ulrich",
			"original_name": "Robert Ulrich",
			"popularity": 0.833,
			"profile_path": null,
			"credit_id": "5b2faa6f92514174700052f2",
			"department": "Sound",
			"job": "Supervising ADR Editor"
		},
		{
			"adult": false,
			"gender": 0,
			"id": 1897498,
			"known_for_department": "Sound",
			"name": "Pamela Bentkowski",
			"original_name": "Pamela Bentkowski",
			"popularity": 0.655,
			"profile_path": null,
			"credit_id": "5b2faaa2c3a3685771007230",
			"department": "Sound",
			"job": "Foley"
		},
		{
			"adult": false,
			"gender": 2,
			"id": 1391679,
			"known_for_department": "Sound",
			"name": "Mike Szakmeister",
			"original_name": "Mike Szakmeister",
			"popularity": 1.173,
			"profile_path": null,
			"credit_id": "5b2faa90c3a36857110065f3",
			"department": "Sound",
			"job": "Supervising Dialogue Editor"
		},
		{
			"adult": false,
			"gender": 2,
			"id": 2071371,
			"known_for_department": "Crew",
			"name": "Andy Evans",
			"original_name": "Andy Evans",
			"popularity": 0.001,
			"profile_path": null,
			"credit_id": "5b2facd8c3a36843c5006cb1",
			"department": "Crew",
			"job": "Special Effects Assistant"
		},
		{
			"adult": false,
			"gender": 0,
			"id": 237398,
			"known_for_department": "Acting",
			"name": "Michael McGovern",
			"original_name": "Michael McGovern",
			"popularity": 0.188,
			"profile_path": null,
			"credit_id": "5b2fb154c3a368580d0067ae",
			"department": "Crew",
			"job": "Visual Effects Editor"
		},
		{
			"adult": false,
			"gender": 1,
			"id": 1338311,
			"known_for_department": "Sound",
			"name": "Linda Di Franco",
			"original_name": "Linda Di Franco",
			"popularity": 1.131,
			"profile_path": null,
			"credit_id": "5b2fa90bc3a36857cf0062b6",
			"department": "Sound",
			"job": "Foley Editor"
		},
		{
			"adult": false,
			"gender": 2,
			"id": 1397846,
			"known_for_department": "Visual Effects",
			"name": "Craig Barron",
			"original_name": "Craig Barron",
			"popularity": 1.926,
			"profile_path": "/Aami37fpHXKCTxReopbTLohgsY1.jpg",
			"credit_id": "5b2fb224c3a3685b99005261",
			"department": "Visual Effects",
			"job": "Visual Effects Supervisor"
		},
		{
			"adult": false,
			"gender": 0,
			"id": 1405235,
			"known_for_department": "Sound",
			"name": "Kerry Dean Williams",
			"original_name": "Kerry Dean Williams",
			"popularity": 0.515,
			"profile_path": null,
			"credit_id": "5b2fa79f9251416fa20051b4",
			"department": "Sound",
			"job": "ADR Editor"
		},
		{
			"adult": false,
			"gender": 2,
			"id": 1344255,
			"known_for_department": "Sound",
			"name": "Anthony Milch",
			"original_name": "Anthony Milch",
			"popularity": 2.281,
			"profile_path": null,
			"credit_id": "5b2fa9420e0a26560600521e",
			"department": "Sound",
			"job": "Sound Editor"
		},
		{
			"adult": false,
			"gender": 0,
			"id": 2071365,
			"known_for_department": "Sound",
			"name": "James Wolvington",
			"original_name": "James Wolvington",
			"popularity": 0.001,
			"profile_path": null,
			"credit_id": "5b2faafdc3a36858cb004afe",
			"department": "Sound",
			"job": "Supervising Sound Editor"
		},
		{
			"adult": false,
			"gender": 0,
			"id": 2071368,
			"known_for_department": "Crew",
			"name": "Thomas D. Bacho Jr.",
			"original_name": "Thomas D. Bacho Jr.",
			"popularity": 0.001,
			"profile_path": null,
			"credit_id": "5b2fac75c3a3685774007705",
			"department": "Crew",
			"job": "Special Effects Technician"
		},
		{
			"adult": false,
			"gender": 2,
			"id": 2071382,
			"known_for_department": "Camera",
			"name": "David Owen",
			"original_name": "David Owen",
			"popularity": 0.001,
			"profile_path": null,
			"credit_id": "5b2fb0ed9251416f83004f99",
			"department": "Camera",
			"job": "Still Photographer"
		},
		{
			"adult": false,
			"gender": 0,
			"id": 1426772,
			"known_for_department": "Visual Effects",
			"name": "Jeff Olson",
			"original_name": "Jeff Olson",
			"popularity": 1.236,
			"profile_path": null,
			"credit_id": "5b2fb18fc3a368575d004abc",
			"department": "Visual Effects",
			"job": "Visual Effects Producer"
		},
		{
			"adult": false,
			"gender": 0,
			"id": 1400566,
			"known_for_department": "Visual Effects",
			"name": "Krystyna Demkowicz",
			"original_name": "Krystyna Demkowicz",
			"popularity": 1.53,
			"profile_path": null,
			"credit_id": "5b2fb1aa0e0a2656df00606a",
			"department": "Visual Effects",
			"job": "Visual Effects Producer"
		},
		{
			"adult": false,
			"gender": 0,
			"id": 1378761,
			"known_for_department": "Visual Effects",
			"name": "Adam Howard",
			"original_name": "Adam Howard",
			"popularity": 0.055,
			"profile_path": null,
			"credit_id": "5b2fb1fbc3a368584b004ac4",
			"department": "Visual Effects",
			"job": "Visual Effects Supervisor"
		},
		{
			"adult": false,
			"gender": 0,
			"id": 1404841,
			"known_for_department": "Sound",
			"name": "Zack Davis",
			"original_name": "Zack Davis",
			"popularity": 0.795,
			"profile_path": null,
			"credit_id": "5b2fa78f0e0a26579600540c",
			"department": "Sound",
			"job": "ADR Editor"
		},
		{
			"adult": false,
			"gender": 2,
			"id": 1551217,
			"known_for_department": "Sound",
			"name": "Tom Perry",
			"original_name": "Tom Perry",
			"popularity": 0.578,
			"profile_path": null,
			"credit_id": "5b2faa2b9251416fa2005353",
			"department": "Sound",
			"job": "Sound Re-Recording Mixer"
		},
		{
			"adult": false,
			"gender": 2,
			"id": 1424167,
			"known_for_department": "Sound",
			"name": "Cameron Frankley",
			"original_name": "Cameron Frankley",
			"popularity": 1.84,
			"profile_path": null,
			"credit_id": "5b2faae40e0a2656b70056ba",
			"department": "Sound",
			"job": "Supervising Sound Editor"
		},
		{
			"adult": false,
			"gender": 0,
			"id": 2071378,
			"known_for_department": "Crew",
			"name": "Habib Zargarpour",
			"original_name": "Habib Zargarpour",
			"popularity": 0.006,
			"profile_path": null,
			"credit_id": "5b2faf089251416fa5005a7f",
			"department": "Crew",
			"job": "CG Supervisor"
		},
		{
			"adult": false,
			"gender": 0,
			"id": 1401105,
			"known_for_department": "Crew",
			"name": "Michael Gleason",
			"original_name": "Michael Gleason",
			"popularity": 1.265,
			"profile_path": null,
			"credit_id": "5b2fb1229251416fa2005743",
			"department": "Crew",
			"job": "Visual Effects Editor"
		},
		{
			"adult": false,
			"gender": 0,
			"id": 2071383,
			"known_for_department": "Visual Effects",
			"name": "David Takemura",
			"original_name": "David Takemura",
			"popularity": 0.001,
			"profile_path": null,
			"credit_id": "5b2fb2110e0a264281005d60",
			"department": "Visual Effects",
			"job": "Visual Effects Supervisor"
		},
		{
			"adult": false,
			"gender": 0,
			"id": 551903,
			"known_for_department": "Costume & Make-Up",
			"name": "Camille Calvet",
			"original_name": "Camille Calvet",
			"popularity": 0.783,
			"profile_path": null,
			"credit_id": "5b2d0fd0c3a3682202003c53",
			"department": "Costume & Make-Up",
			"job": "Makeup Artist"
		},
		{
			"adult": false,
			"gender": 0,
			"id": 1358076,
			"known_for_department": "Costume & Make-Up",
			"name": "Ellis Burman Jr.",
			"original_name": "Ellis Burman Jr.",
			"popularity": 0.612,
			"profile_path": null,
			"credit_id": "5b2d1084925141351f00414c",
			"department": "Costume & Make-Up",
			"job": "Makeup Artist"
		},
		{
			"adult": false,
			"gender": 0,
			"id": 2070276,
			"known_for_department": "Costume & Make-Up",
			"name": "Derik Wingo",
			"original_name": "Derik Wingo",
			"popularity": 0.001,
			"profile_path": null,
			"credit_id": "5b2d11d992514135120046d3",
			"department": "Costume & Make-Up",
			"job": "Special Effects Makeup Artist"
		},
		{
			"adult": false,
			"gender": 0,
			"id": 2070274,
			"known_for_department": "Costume & Make-Up",
			"name": "R. Stephen Weber",
			"original_name": "R. Stephen Weber",
			"popularity": 0.001,
			"profile_path": null,
			"credit_id": "5b2d10320e0a26286e00470d",
			"department": "Costume & Make-Up",
			"job": "Makeup Artist"
		},
		{
			"adult": false,
			"gender": 2,
			"id": 16519,
			"known_for_department": "Costume & Make-Up",
			"name": "Michael Westmore",
			"original_name": "Michael Westmore",
			"popularity": 1.928,
			"profile_path": "/2GjBNS64nYQOiyV3COKqR4Wjlun.jpg",
			"credit_id": "5b2d10b69251413533003bc6",
			"department": "Costume & Make-Up",
			"job": "Makeup Supervisor"
		},
		{
			"adult": false,
			"gender": 0,
			"id": 1712068,
			"known_for_department": "Costume & Make-Up",
			"name": "June Westmore",
			"original_name": "June Westmore",
			"popularity": 0.71,
			"profile_path": null,
			"credit_id": "5b2d1044925141351f004139",
			"department": "Costume & Make-Up",
			"job": "Makeup Artist"
		},
		{
			"adult": false,
			"gender": 2,
			"id": 1327909,
			"known_for_department": "Costume & Make-Up",
			"name": "Scott Wheeler",
			"original_name": "Scott Wheeler",
			"popularity": 0.578,
			"profile_path": null,
			"credit_id": "5b2d1065c3a368221d004c68",
			"department": "Costume & Make-Up",
			"job": "Makeup Artist"
		},
		{
			"adult": false,
			"gender": 1,
			"id": 2024334,
			"known_for_department": "Costume & Make-Up",
			"name": "Tina Hoffman",
			"original_name": "Tina Hoffman",
			"popularity": 0.239,
			"profile_path": null,
			"credit_id": "5b2d0ff1925141352800373d",
			"department": "Costume & Make-Up",
			"job": "Makeup Artist"
		},
		{
			"adult": false,
			"gender": 2,
			"id": 16519,
			"known_for_department": "Costume & Make-Up",
			"name": "Michael Westmore",
			"original_name": "Michael Westmore",
			"popularity": 1.928,
			"profile_path": "/2GjBNS64nYQOiyV3COKqR4Wjlun.jpg",
			"credit_id": "5b2d10a50e0a2628560045b8",
			"department": "Costume & Make-Up",
			"job": "Makeup Designer"
		},
		{
			"adult": false,
			"gender": 0,
			"id": 2070275,
			"known_for_department": "Costume & Make-Up",
			"name": "Toby Lamm",
			"original_name": "Toby Lamm",
			"popularity": 0.469,
			"profile_path": null,
			"credit_id": "5b2d118a0e0a262854004717",
			"department": "Costume & Make-Up",
			"job": "Special Effects Makeup Artist"
		},
		{
			"adult": false,
			"gender": 2,
			"id": 1213783,
			"known_for_department": "Production",
			"name": "Rick Berman",
			"original_name": "Rick Berman",
			"popularity": 2.42,
			"profile_path": "/mEznRUFYLmpD6jPPeZKLWkHtPdn.jpg",
			"credit_id": "5b2d0e0ac3a3682208003c8d",
			"department": "Production",
			"job": "Producer"
		},
		{
			"adult": false,
			"gender": 2,
			"id": 2385,
			"known_for_department": "Writing",
			"name": "Ronald D. Moore",
			"original_name": "Ronald D. Moore",
			"popularity": 7.074,
			"profile_path": "/6A086Blwpv0nuckrzPgvETlkfo1.jpg",
			"credit_id": "5b2d0eadc3a36878530002ec",
			"department": "Writing",
			"job": "Story"
		},
		{
			"adult": false,
			"gender": 0,
			"id": 1536381,
			"known_for_department": "Costume & Make-Up",
			"name": "Lee Ann Brittenham",
			"original_name": "Lee Ann Brittenham",
			"popularity": 0.799,
			"profile_path": null,
			"credit_id": "5b2d0f3ac3a3682217004de8",
			"department": "Costume & Make-Up",
			"job": "Hairstylist"
		},
		{
			"adult": false,
			"gender": 2,
			"id": 2070273,
			"known_for_department": "Costume & Make-Up",
			"name": "Gilbert A. Mosko",
			"original_name": "Gilbert A. Mosko",
			"popularity": 0.911,
			"profile_path": null,
			"credit_id": "5b2d10210e0a267f64000223",
			"department": "Costume & Make-Up",
			"job": "Makeup Artist"
		},
		{
			"adult": false,
			"gender": 0,
			"id": 1072007,
			"known_for_department": "Costume & Make-Up",
			"name": "Barbara Ronci",
			"original_name": "Barbara Ronci",
			"popularity": 0.001,
			"profile_path": null,
			"credit_id": "5b2d0f6592514134e90045ea",
			"department": "Costume & Make-Up",
			"job": "Hairstylist"
		},
		{
			"adult": false,
			"gender": 0,
			"id": 1948536,
			"known_for_department": "Costume & Make-Up",
			"name": "Brad Look",
			"original_name": "Brad Look",
			"popularity": 0.518,
			"profile_path": null,
			"credit_id": "5b2d1000c3a3682217004e37",
			"department": "Costume & Make-Up",
			"job": "Makeup Artist"
		},
		{
			"adult": false,
			"gender": 0,
			"id": 1309209,
			"known_for_department": "Costume & Make-Up",
			"name": "James MacKinnon",
			"original_name": "James MacKinnon",
			"popularity": 0.888,
			"profile_path": null,
			"credit_id": "5b2d10d2c3a3682217004e8b",
			"department": "Costume & Make-Up",
			"job": "Prosthetic Makeup Artist"
		},
		{
			"adult": false,
			"gender": 0,
			"id": 1667251,
			"known_for_department": "Crew",
			"name": "Belinda Bryant",
			"original_name": "Belinda Bryant",
			"popularity": 0.015,
			"profile_path": null,
			"credit_id": "5b2d0faf0e0a2628690045d8",
			"department": "Costume & Make-Up",
			"job": "Makeup Artist"
		},
		{
			"adult": false,
			"gender": 2,
			"id": 1647987,
			"known_for_department": "Costume & Make-Up",
			"name": "Mark Bussan",
			"original_name": "Mark Bussan",
			"popularity": 0.265,
			"profile_path": null,
			"credit_id": "5b2d0fc0c3a368221400464e",
			"department": "Costume & Make-Up",
			"job": "Makeup Artist"
		},
		{
			"adult": false,
			"gender": 2,
			"id": 957990,
			"known_for_department": "Costume & Make-Up",
			"name": "Monty Westmore",
			"original_name": "Monty Westmore",
			"popularity": 2.55,
			"profile_path": null,
			"credit_id": "5b2d105592514135090040a2",
			"department": "Costume & Make-Up",
			"job": "Makeup Artist"
		},
		{
			"adult": false,
			"gender": 0,
			"id": 2024319,
			"known_for_department": "Costume & Make-Up",
			"name": "Mary Kay Morse",
			"original_name": "Mary Kay Morse",
			"popularity": 0.876,
			"profile_path": null,
			"credit_id": "5b2d101192514135400044f3",
			"department": "Costume & Make-Up",
			"job": "Makeup Artist"
		},
		{
			"adult": false,
			"gender": 0,
			"id": 1926186,
			"known_for_department": "Costume & Make-Up",
			"name": "Danny Valencia",
			"original_name": "Danny Valencia",
			"popularity": 0.001,
			"profile_path": null,
			"credit_id": "5b2d0f7c0e0a2628720045ee",
			"department": "Costume & Make-Up",
			"job": "Hairstylist"
		},
		{
			"adult": false,
			"gender": 0,
			"id": 1527705,
			"known_for_department": "Costume & Make-Up",
			"name": "Joe Podnar",
			"original_name": "Joe Podnar",
			"popularity": 0.007,
			"profile_path": null,
			"credit_id": "5b2d1199c3a3682217004ee2",
			"department": "Costume & Make-Up",
			"job": "Special Effects Makeup Artist"
		},
		{
			"adult": false,
			"gender": 0,
			"id": 1536916,
			"known_for_department": "Costume & Make-Up",
			"name": "Chris McBee",
			"original_name": "Chris McBee",
			"popularity": 0.143,
			"profile_path": null,
			"credit_id": "5b2d0f5292514134eb0042a1",
			"department": "Costume & Make-Up",
			"job": "Hairstylist"
		},
		{
			"adult": false,
			"gender": 1,
			"id": 1338146,
			"known_for_department": "Costume & Make-Up",
			"name": "Natalie Wood",
			"original_name": "Natalie Wood",
			"popularity": 1.144,
			"profile_path": null,
			"credit_id": "5b2d10749251413528003750",
			"department": "Costume & Make-Up",
			"job": "Makeup Artist"
		},
		{
			"adult": false,
			"gender": 2,
			"id": 2386,
			"known_for_department": "Production",
			"name": "Brannon Braga",
			"original_name": "Brannon Braga",
			"popularity": 4.955,
			"profile_path": "/e2lvaxWUG5dcbl36BEi4po6M0YB.jpg",
			"credit_id": "5b2d0e92c3a3682220004838",
			"department": "Writing",
			"job": "Story"
		},
		{
			"adult": false,
			"gender": 0,
			"id": 1316003,
			"known_for_department": "Costume & Make-Up",
			"name": "Jane Galli",
			"original_name": "Jane Galli",
			"popularity": 0.993,
			"profile_path": null,
			"credit_id": "5b2d115992514135390039fa",
			"department": "Costume & Make-Up",
			"job": "Special Effects Makeup Artist"
		},
		{
			"adult": false,
			"gender": 2,
			"id": 1213783,
			"known_for_department": "Production",
			"name": "Rick Berman",
			"original_name": "Rick Berman",
			"popularity": 2.42,
			"profile_path": "/mEznRUFYLmpD6jPPeZKLWkHtPdn.jpg",
			"credit_id": "5b2d0e7f92514134e90045a5",
			"department": "Writing",
			"job": "Story"
		},
		{
			"adult": false,
			"gender": 2,
			"id": 1206190,
			"known_for_department": "Crew",
			"name": "Jake Garber",
			"original_name": "Jake Garber",
			"popularity": 1.394,
			"profile_path": "/bYUTYworrOBjM6fCK6QBNuJG3pI.jpg",
			"credit_id": "5b2d117ac3a368222c0048ae",
			"department": "Costume & Make-Up",
			"job": "Special Effects Makeup Artist"
		},
		{
			"adult": false,
			"gender": 0,
			"id": 2070788,
			"known_for_department": "Art",
			"name": "Glen R. Feldman",
			"original_name": "Glen R. Feldman",
			"popularity": 0.001,
			"profile_path": null,
			"credit_id": "5b2e5d4e0e0a2657bf005d8d",
			"department": "Art",
			"job": "Assistant Property Master"
		},
		{
			"adult": false,
			"gender": 0,
			"id": 1637979,
			"known_for_department": "Art",
			"name": "Linda A. King",
			"original_name": "Linda A. King",
			"popularity": 0.006,
			"profile_path": null,
			"credit_id": "5b2e5f8f9251416e04004ca7",
			"department": "Art",
			"job": "Set Designer"
		},
		{
			"adult": false,
			"gender": 0,
			"id": 2070796,
			"known_for_department": "Art",
			"name": "Philip Calhoun",
			"original_name": "Philip Calhoun",
			"popularity": 0.001,
			"profile_path": null,
			"credit_id": "5b2e5ff10e0a2657ca00585d",
			"department": "Art",
			"job": "Set Dresser"
		},
		{
			"adult": false,
			"gender": 2,
			"id": 25601,
			"known_for_department": "Camera",
			"name": "Lowell Peterson",
			"original_name": "Lowell Peterson",
			"popularity": 0.049,
			"profile_path": null,
			"credit_id": "5b2e6142c3a368532f006688",
			"department": "Camera",
			"job": "Additional Photography"
		},
		{
			"adult": false,
			"gender": 2,
			"id": 1835194,
			"known_for_department": "Art",
			"name": "Thomas J. Arp",
			"original_name": "Thomas J. Arp",
			"popularity": 0.14,
			"profile_path": null,
			"credit_id": "5b2e5d640e0a2657e70061c2",
			"department": "Art",
			"job": "Construction Coordinator"
		},
		{
			"adult": false,
			"gender": 0,
			"id": 2070792,
			"known_for_department": "Art",
			"name": "Barry Tugendhaft",
			"original_name": "Barry Tugendhaft",
			"popularity": 0.001,
			"profile_path": null,
			"credit_id": "5b2e5df50e0a2657d0005e44",
			"department": "Art",
			"job": "Greensman"
		},
		{
			"adult": false,
			"gender": 0,
			"id": 2070793,
			"known_for_department": "Art",
			"name": "Brent W. Bell",
			"original_name": "Brent W. Bell",
			"popularity": 0.001,
			"profile_path": null,
			"credit_id": "5b2e5e1e9251416e290052ec",
			"department": "Art",
			"job": "Leadman"
		},
		{
			"adult": false,
			"gender": 2,
			"id": 1421252,
			"known_for_department": "Lighting",
			"name": "Tim Marshall",
			"original_name": "Tim Marshall",
			"popularity": 0.195,
			"profile_path": null,
			"credit_id": "5b2e61789251416e1f006043",
			"department": "Lighting",
			"job": "Assistant Chief Lighting Technician"
		},
		{
			"adult": false,
			"gender": 0,
			"id": 2070803,
			"known_for_department": "Camera",
			"name": "J. Chuck Biagio",
			"original_name": "J. Chuck Biagio",
			"popularity": 0.001,
			"profile_path": null,
			"credit_id": "5b2e61b49251416e55005977",
			"department": "Camera",
			"job": "Best Boy Grip"
		},
		{
			"adult": false,
			"gender": 0,
			"id": 1341852,
			"known_for_department": "Art",
			"name": "Dean Wilson",
			"original_name": "Dean Wilson",
			"popularity": 0.06,
			"profile_path": null,
			"credit_id": "5b2e5f47c3a368532f00652f",
			"department": "Art",
			"job": "Property Master"
		},
		{
			"adult": false,
			"gender": 0,
			"id": 1398939,
			"known_for_department": "Art",
			"name": "Penny Smartt-Juday",
			"original_name": "Penny Smartt-Juday",
			"popularity": 0.384,
			"profile_path": null,
			"credit_id": "5b2e5d3b0e0a2657d7005852",
			"department": "Art",
			"job": "Art Department Coordinator"
		},
		{
			"adult": false,
			"gender": 0,
			"id": 1863270,
			"known_for_department": "Costume & Make-Up",
			"name": "Larry D. Koszakovszky",
			"original_name": "Larry D. Koszakovszky",
			"popularity": 0.001,
			"profile_path": null,
			"credit_id": "5b2e60069251416e1f005f59",
			"department": "Art",
			"job": "Set Dresser"
		},
		{
			"adult": false,
			"gender": 0,
			"id": 1594907,
			"known_for_department": "Art",
			"name": "Clete Cetrone",
			"original_name": "Clete Cetrone",
			"popularity": 0.599,
			"profile_path": null,
			"credit_id": "5b2e5d880e0a2657ec005718",
			"department": "Art",
			"job": "Construction Foreman"
		},
		{
			"adult": false,
			"gender": 0,
			"id": 2070795,
			"known_for_department": "Art",
			"name": "Elijah Bryant",
			"original_name": "Elijah Bryant",
			"popularity": 0.001,
			"profile_path": null,
			"credit_id": "5b2e5fe19251416e4a0057f7",
			"department": "Art",
			"job": "Set Dresser"
		},
		{
			"adult": false,
			"gender": 0,
			"id": 1536398,
			"known_for_department": "Costume & Make-Up",
			"name": "Leah Brown",
			"original_name": "Leah Brown",
			"popularity": 0.244,
			"profile_path": null,
			"credit_id": "5b2e65c30e0a2657da006051",
			"department": "Costume & Make-Up",
			"job": "Costumer"
		},
		{
			"adult": false,
			"gender": 2,
			"id": 1423834,
			"known_for_department": "Costume & Make-Up",
			"name": "Joe Colwell",
			"original_name": "Joe Colwell",
			"popularity": 0.035,
			"profile_path": null,
			"credit_id": "5b2e5e880e0a2657ea005ad9",
			"department": "Art",
			"job": "Painter"
		},
		{
			"adult": false,
			"gender": 2,
			"id": 2070801,
			"known_for_department": "Lighting",
			"name": "Francis X. Valdez III",
			"original_name": "Francis X. Valdez III",
			"popularity": 0.029,
			"profile_path": null,
			"credit_id": "5b2e61969251416e06005d5f",
			"department": "Lighting",
			"job": "Assistant Chief Lighting Technician"
		},
		{
			"adult": false,
			"gender": 0,
			"id": 1492926,
			"known_for_department": "Camera",
			"name": "Henryk Cymerman",
			"original_name": "Henryk Cymerman",
			"popularity": 0.001,
			"profile_path": null,
			"credit_id": "5b2e62b50e0a2657e0005f62",
			"department": "Camera",
			"job": "Second Unit Director of Photography"
		},
		{
			"adult": false,
			"gender": 2,
			"id": 1783639,
			"known_for_department": "Camera",
			"name": "Michael D. Weldon",
			"original_name": "Michael D. Weldon",
			"popularity": 0.714,
			"profile_path": null,
			"credit_id": "5b2e63279251416e04004e81",
			"department": "Camera",
			"job": "First Assistant Camera"
		},
		{
			"adult": false,
			"gender": 0,
			"id": 2070789,
			"known_for_department": "Art",
			"name": "Curt Jones",
			"original_name": "Curt Jones",
			"popularity": 0.001,
			"profile_path": null,
			"credit_id": "5b2e5da29251416e04004bc4",
			"department": "Art",
			"job": "Construction Foreman"
		},
		{
			"adult": false,
			"gender": 0,
			"id": 53026,
			"known_for_department": "Art",
			"name": "Les Gobruegge",
			"original_name": "Les Gobruegge",
			"popularity": 0.001,
			"profile_path": null,
			"credit_id": "5b2e5fa20e0a2657c8005b98",
			"department": "Art",
			"job": "Set Designer"
		},
		{
			"adult": false,
			"gender": 0,
			"id": 1552035,
			"known_for_department": "Sound",
			"name": "Nick Vidar",
			"original_name": "Nick Vidar",
			"popularity": 1.014,
			"profile_path": null,
			"credit_id": "5b2e67cb0e0a2657e3006034",
			"department": "Sound",
			"job": "Music Programmer"
		},
		{
			"adult": false,
			"gender": 1,
			"id": 1411279,
			"known_for_department": "Directing",
			"name": "Judi Brown",
			"original_name": "Judi Brown",
			"popularity": 0.001,
			"profile_path": null,
			"credit_id": "5b2e687dc3a368533b006267",
			"department": "Directing",
			"job": "Script Supervisor"
		},
		{
			"adult": false,
			"gender": 0,
			"id": 2070815,
			"known_for_department": "Costume & Make-Up",
			"name": "Matthew A. Hoffman",
			"original_name": "Matthew A. Hoffman",
			"popularity": 0.001,
			"profile_path": null,
			"credit_id": "5b2e65fc0e0a2657ca005baa",
			"department": "Costume & Make-Up",
			"job": "Key Costumer"
		},
		{
			"adult": false,
			"gender": 0,
			"id": 21801,
			"known_for_department": "Sound",
			"name": "Lee Scott",
			"original_name": "Lee Scott",
			"popularity": 1.254,
			"profile_path": null,
			"credit_id": "5b2e677ec3a368534a0051be",
			"department": "Sound",
			"job": "Music Editor"
		},
		{
			"adult": false,
			"gender": 2,
			"id": 66688,
			"known_for_department": "Art",
			"name": "William Hawkins",
			"original_name": "William Hawkins",
			"popularity": 1.742,
			"profile_path": null,
			"credit_id": "5b2e5fc70e0a2657ca00583c",
			"department": "Art",
			"job": "Set Designer"
		},
		{
			"adult": false,
			"gender": 0,
			"id": 1735477,
			"known_for_department": "Crew",
			"name": "Wayne Tidwell",
			"original_name": "Wayne Tidwell",
			"popularity": 0.601,
			"profile_path": null,
			"credit_id": "5b2e63ac9251416e5200488c",
			"department": "Crew",
			"job": "Video Assist Operator"
		},
		{
			"adult": false,
			"gender": 1,
			"id": 2070811,
			"known_for_department": "Costume & Make-Up",
			"name": "Gina DeDomenico Flanagan",
			"original_name": "Gina DeDomenico Flanagan",
			"popularity": 0.001,
			"profile_path": null,
			"credit_id": "5b2e65580e0a2657d4005dea",
			"department": "Costume & Make-Up",
			"job": "Costume Illustrator"
		},
		{
			"adult": false,
			"gender": 2,
			"id": 1083680,
			"known_for_department": "Editing",
			"name": "Tim Board",
			"original_name": "Tim Board",
			"popularity": 0.237,
			"profile_path": null,
			"credit_id": "5b2e6647c3a3685338006f2a",
			"department": "Editing",
			"job": "Additional Editor"
		},
		{
			"adult": false,
			"gender": 0,
			"id": 1934395,
			"known_for_department": "Art",
			"name": "Gary Metzen",
			"original_name": "Gary Metzen",
			"popularity": 0.548,
			"profile_path": null,
			"credit_id": "5b2e5ea50e0a2657c5005ecf",
			"department": "Art",
			"job": "Painter"
		},
		{
			"adult": false,
			"gender": 0,
			"id": 1422865,
			"known_for_department": "Art",
			"name": "Roger L. King",
			"original_name": "Roger L. King",
			"popularity": 0.153,
			"profile_path": null,
			"credit_id": "5b2e5f320e0a2657d0005efc",
			"department": "Art",
			"job": "Property Master"
		},
		{
			"adult": false,
			"gender": 0,
			"id": 2070805,
			"known_for_department": "Camera",
			"name": "John Young",
			"original_name": "John Young",
			"popularity": 0.001,
			"profile_path": null,
			"credit_id": "5b2e61dd9251416e00005253",
			"department": "Camera",
			"job": "Camera Loader"
		},
		{
			"adult": false,
			"gender": 1,
			"id": 1392896,
			"known_for_department": "Art",
			"name": "Martha Johnston",
			"original_name": "Martha Johnston",
			"popularity": 0.827,
			"profile_path": null,
			"credit_id": "5b2e5fb39251416e1f005ecb",
			"department": "Art",
			"job": "Set Designer"
		},
		{
			"adult": false,
			"gender": 0,
			"id": 2070810,
			"known_for_department": "Lighting",
			"name": "John D. Babin",
			"original_name": "John D. Babin",
			"popularity": 0.001,
			"profile_path": null,
			"credit_id": "5b2e637ac3a368533d0046f4",
			"department": "Lighting",
			"job": "Rigging Grip"
		},
		{
			"adult": false,
			"gender": 2,
			"id": 1693502,
			"known_for_department": "Editing",
			"name": "Mike Milliken",
			"original_name": "Mike Milliken",
			"popularity": 1.041,
			"profile_path": null,
			"credit_id": "5b2e666a0e0a2657bf0062d4",
			"department": "Editing",
			"job": "Color Timer"
		},
		{
			"adult": false,
			"gender": 0,
			"id": 1673640,
			"known_for_department": "Visual Effects",
			"name": "John Mann",
			"original_name": "John Mann",
			"popularity": 0.395,
			"profile_path": null,
			"credit_id": "5b2e604a0e0a2657d4005b3c",
			"department": "Art",
			"job": "Storyboard Artist"
		},
		{
			"adult": false,
			"gender": 2,
			"id": 1398127,
			"known_for_department": "Camera",
			"name": "William D. Barber",
			"original_name": "William D. Barber",
			"popularity": 1.053,
			"profile_path": null,
			"credit_id": "5b2e624fc3a3685322006792",
			"department": "Camera",
			"job": "Camera Operator"
		},
		{
			"adult": false,
			"gender": 0,
			"id": 1823796,
			"known_for_department": "Camera",
			"name": "Alan Shultz",
			"original_name": "Alan Shultz",
			"popularity": 0.669,
			"profile_path": null,
			"credit_id": "5b2e62ccc3a36853220067d2",
			"department": "Camera",
			"job": "Dolly Grip"
		},
		{
			"adult": false,
			"gender": 0,
			"id": 2034923,
			"known_for_department": "Costume & Make-Up",
			"name": "Yvette Ammon",
			"original_name": "Yvette Ammon",
			"popularity": 0.001,
			"profile_path": null,
			"credit_id": "5b2e660fc3a36853470053ec",
			"department": "Costume & Make-Up",
			"job": "Set Costumer"
		},
		{
			"adult": false,
			"gender": 0,
			"id": 1790024,
			"known_for_department": "Crew",
			"name": "Bogdan Iofciulescu",
			"original_name": "Bogdan Iofciulescu",
			"popularity": 0.211,
			"profile_path": null,
			"credit_id": "5b2e6392c3a3685340006c76",
			"department": "Crew",
			"job": "Techno Crane Operator"
		},
		{
			"adult": false,
			"gender": 0,
			"id": 1702130,
			"known_for_department": "Editing",
			"name": "Bryan McMahan",
			"original_name": "Bryan McMahan",
			"popularity": 0.001,
			"profile_path": null,
			"credit_id": "5b2e6683c3a368534a005128",
			"department": "Editing",
			"job": "Colorist"
		},
		{
			"adult": false,
			"gender": 2,
			"id": 91245,
			"known_for_department": "Sound",
			"name": "Arthur Morton",
			"original_name": "Arthur Morton",
			"popularity": 1.638,
			"profile_path": null,
			"credit_id": "5b2e681ac3a36853470054e3",
			"department": "Sound",
			"job": "Orchestrator"
		},
		{
			"adult": false,
			"gender": 0,
			"id": 1404199,
			"known_for_department": "Crew",
			"name": "Jennifer Bender",
			"original_name": "Jennifer Bender",
			"popularity": 0.489,
			"profile_path": null,
			"credit_id": "5b2e64439251416e4300510a",
			"department": "Production",
			"job": "Extras Casting"
		},
		{
			"adult": false,
			"gender": 0,
			"id": 2070813,
			"known_for_department": "Costume & Make-Up",
			"name": "Heidi Odum Strasburg",
			"original_name": "Heidi Odum Strasburg",
			"popularity": 0.001,
			"profile_path": null,
			"credit_id": "5b2e6595c3a368534a0050ad",
			"department": "Costume & Make-Up",
			"job": "Costumer"
		},
		{
			"adult": false,
			"gender": 0,
			"id": 1414556,
			"known_for_department": "Costume & Make-Up",
			"name": "Joe Diaz",
			"original_name": "Joe Diaz",
			"popularity": 0.001,
			"profile_path": null,
			"credit_id": "5b2e65a90e0a2657da006031",
			"department": "Costume & Make-Up",
			"job": "Costumer"
		},
		{
			"adult": false,
			"gender": 0,
			"id": 2070814,
			"known_for_department": "Costume & Make-Up",
			"name": "Christine Heinz",
			"original_name": "Christine Heinz",
			"popularity": 0.001,
			"profile_path": null,
			"credit_id": "5b2e65e50e0a2657e3005f1a",
			"department": "Costume & Make-Up",
			"job": "Key Costumer"
		},
		{
			"adult": false,
			"gender": 0,
			"id": 1603908,
			"known_for_department": "Sound",
			"name": "Bruce Botnick",
			"original_name": "Bruce Botnick",
			"popularity": 0.599,
			"profile_path": null,
			"credit_id": "5b2e67a99251416e52004a7e",
			"department": "Sound",
			"job": "Music Editor"
		},
		{
			"adult": false,
			"gender": 0,
			"id": 1531884,
			"known_for_department": "Camera",
			"name": "Randy Feemster",
			"original_name": "Randy Feemster",
			"popularity": 0.001,
			"profile_path": null,
			"credit_id": "5b2e6238c3a368532f006713",
			"department": "Camera",
			"job": "Camera Operator"
		},
		{
			"adult": false,
			"gender": 2,
			"id": 139699,
			"known_for_department": "Camera",
			"name": "Norman G. Langley",
			"original_name": "Norman G. Langley",
			"popularity": 0.675,
			"profile_path": null,
			"credit_id": "5b2e62e9c3a368533200636a",
			"department": "Lighting",
			"job": "Electrician"
		},
		{
			"adult": false,
			"gender": 0,
			"id": 2070800,
			"known_for_department": "Camera",
			"name": "Christian H. Burton",
			"original_name": "Christian H. Burton",
			"popularity": 0.001,
			"profile_path": null,
			"credit_id": "5b2e615dc3a3685340006ae7",
			"department": "Camera",
			"job": "Assistant Camera"
		},
		{
			"adult": false,
			"gender": 0,
			"id": 1377132,
			"known_for_department": "Camera",
			"name": "David Luckenbach",
			"original_name": "David Luckenbach",
			"popularity": 1.515,
			"profile_path": null,
			"credit_id": "5b2e62620e0a2657d7005b3f",
			"department": "Camera",
			"job": "Steadicam Operator"
		},
		{
			"adult": false,
			"gender": 2,
			"id": 936765,
			"known_for_department": "Sound",
			"name": "Jeff Atmajian",
			"original_name": "Jeff Atmajian",
			"popularity": 6.254,
			"profile_path": "/118QAIvoXmXVK0U2XqKohpE4CfT.jpg",
			"credit_id": "5b2e67ffc3a3685329006fb2",
			"department": "Sound",
			"job": "Orchestrator"
		},
		{
			"adult": false,
			"gender": 0,
			"id": 2070790,
			"known_for_department": "Art",
			"name": "Frank Leasure",
			"original_name": "Frank Leasure",
			"popularity": 0.001,
			"profile_path": null,
			"credit_id": "5b2e5db7c3a368532f006408",
			"department": "Art",
			"job": "Construction Foreman"
		},
		{
			"adult": false,
			"gender": 0,
			"id": 2070798,
			"known_for_department": "Art",
			"name": "Jerry Wax",
			"original_name": "Jerry Wax",
			"popularity": 0.001,
			"profile_path": null,
			"credit_id": "5b2e60199251416e290053fb",
			"department": "Art",
			"job": "Set Dresser"
		},
		{
			"adult": false,
			"gender": 2,
			"id": 1536458,
			"known_for_department": "Lighting",
			"name": "Pat Blymyer",
			"original_name": "Pat Blymyer",
			"popularity": 0.54,
			"profile_path": null,
			"credit_id": "5b2e6273c3a36853200068b0",
			"department": "Lighting",
			"job": "Chief Lighting Technician"
		},
		{
			"adult": false,
			"gender": 2,
			"id": 1656421,
			"known_for_department": "Lighting",
			"name": "Mike Weathers",
			"original_name": "Mike Weathers",
			"popularity": 0.325,
			"profile_path": null,
			"credit_id": "5b2e6284c3a368532f006746",
			"department": "Lighting",
			"job": "Chief Lighting Technician"
		},
		{
			"adult": false,
			"gender": 0,
			"id": 1174405,
			"known_for_department": "Camera",
			"name": "Michael Condro",
			"original_name": "Michael Condro",
			"popularity": 0.116,
			"profile_path": null,
			"credit_id": "5b2e62fc0e0a2657bf0060e7",
			"department": "Camera",
			"job": "First Assistant Camera"
		},
		{
			"adult": false,
			"gender": 0,
			"id": 2070808,
			"known_for_department": "Camera",
			"name": "Tom Keefer",
			"original_name": "Tom Keefer",
			"popularity": 0.01,
			"profile_path": null,
			"credit_id": "5b2e6344c3a36853350057eb",
			"department": "Camera",
			"job": "Key Grip"
		},
		{
			"adult": false,
			"gender": 0,
			"id": 2070809,
			"known_for_department": "Lighting",
			"name": "Gregory Shummon",
			"original_name": "Gregory Shummon",
			"popularity": 0.008,
			"profile_path": null,
			"credit_id": "5b2e63599251416e1f006192",
			"department": "Lighting",
			"job": "Lighting Technician"
		},
		{
			"adult": false,
			"gender": 0,
			"id": 2070812,
			"known_for_department": "Costume & Make-Up",
			"name": "Sonny Merritt",
			"original_name": "Sonny Merritt",
			"popularity": 0.001,
			"profile_path": null,
			"credit_id": "5b2e6581c3a3685322006985",
			"department": "Costume & Make-Up",
			"job": "Costumer"
		},
		{
			"adult": false,
			"gender": 2,
			"id": 1344273,
			"known_for_department": "Sound",
			"name": "Cliff Kohlweck",
			"original_name": "Cliff Kohlweck",
			"popularity": 0.701,
			"profile_path": null,
			"credit_id": "5b2e6760c3a3685340006ef6",
			"department": "Sound",
			"job": "Music Editor"
		},
		{
			"adult": false,
			"gender": 0,
			"id": 2004998,
			"known_for_department": "Camera",
			"name": "Mark Santoni",
			"original_name": "Mark Santoni",
			"popularity": 0.582,
			"profile_path": null,
			"credit_id": "5b2e63149251416e0c005dc3",
			"department": "Camera",
			"job": "First Assistant Camera"
		},
		{
			"adult": false,
			"gender": 1,
			"id": 1899435,
			"known_for_department": "Editing",
			"name": "Theresa Repola Mohammed",
			"original_name": "Theresa Repola Mohammed",
			"popularity": 1.584,
			"profile_path": null,
			"credit_id": "5b2e66989251416e1b005a35",
			"department": "Editing",
			"job": "Negative Cutter"
		},
		{
			"adult": false,
			"gender": 2,
			"id": 16161,
			"known_for_department": "Sound",
			"name": "Kenneth Hall",
			"original_name": "Kenneth Hall",
			"popularity": 0.946,
			"profile_path": null,
			"credit_id": "5b2e678fc3a3685340006f0e",
			"department": "Sound",
			"job": "Music Editor"
		},
		{
			"adult": false,
			"gender": 2,
			"id": 1089637,
			"known_for_department": "Acting",
			"name": "John Kay",
			"original_name": "John Kay",
			"popularity": 0.109,
			"profile_path": "/fADGJxZ4uTCuCwjknOFSpqT5v2R.jpg",
			"credit_id": "66b882ff64cd9b5821bbfc50",
			"department": "Sound",
			"job": "Songs"
		},
		{
			"adult": false,
			"gender": 2,
			"id": 16522,
			"known_for_department": "Crew",
			"name": "Jimmy Nickerson",
			"original_name": "Jimmy Nickerson",
			"popularity": 1.337,
			"profile_path": "/zidbZdFLUj5DqmZT7yAbp3wEzmr.jpg",
			"credit_id": "5c24a2ac92514167efc6dfab",
			"department": "Crew",
			"job": "Stunts"
		},
		{
			"adult": false,
			"gender": 2,
			"id": 1401796,
			"known_for_department": "Visual Effects",
			"name": "John Knoll",
			"original_name": "John Knoll",
			"popularity": 1.336,
			"profile_path": "/fI7BXLxINkUnGr51mllgOb4a7Gz.jpg",
			"credit_id": "5ed0116c21c4ca0020def8be",
			"department": "Visual Effects",
			"job": "Visual Effects Supervisor"
		},
		{
			"adult": false,
			"gender": 2,
			"id": 1745,
			"known_for_department": "Writing",
			"name": "Gene Roddenberry",
			"original_name": "Gene Roddenberry",
			"popularity": 6.684,
			"profile_path": "/qY3gWqAMDrrvNVUrwZ8lSa4IKtS.jpg",
			"credit_id": "674222547b825e685b4e6634",
			"department": "Writing",
			"job": "Original Series Creator"
		},
		{
			"adult": false,
			"gender": 2,
			"id": 1761,
			"known_for_department": "Sound",
			"name": "Alexander Courage",
			"original_name": "Alexander Courage",
			"popularity": 2.566,
			"profile_path": "/nVTrM70knWjQcOvATsu2Uric9sl.jpg",
			"credit_id": "675e4624204f3b5b4830290d",
			"department": "Sound",
			"job": "Orchestrator"
		}
	]
}
